limonada/__init__.py
limonada/limon.py
limonada-0.0.1.dist-info/entry_points.txt
limonada-0.0.1.dist-info/COPYING
limonada-0.0.1.dist-info/WHEEL
limonada-0.0.1.dist-info/METADATA
limonada-0.0.1.dist-info/RECORD
