Metadata-Version: 2.3
Name: LiMonaDA
Version: 0.0.1
Summary: Lighweight Monitor and Data Analyzer
Author-email: David Palao <david.palao@gmail.com>
Classifier: Development Status :: 1 - Planning
Classifier: Environment :: Console
Classifier: Environment :: No Input/Output (Daemon)
Classifier: Framework :: AsyncIO
Classifier: Intended Audience :: System Administrators
Classifier: License :: OSI Approved :: GNU General Public License v3 or later (GPLv3+)
Classifier: Natural Language :: English
Classifier: Programming Language :: Python :: 3
Classifier: Programming Language :: Python :: 3.12
Classifier: Operating System :: POSIX :: Linux
Classifier: Programming Language :: Python :: Implementation :: CPython
Classifier: Topic :: System :: Monitoring
Requires-Dist: pytest ; extra == "test"
Project-URL: Home, https://gitlab.gwdg.de/david.palao/limonada
Provides-Extra: test
